drf_typescript_generator/__init__.py
drf_typescript_generator/globals.py
drf_typescript_generator/management/commands/generate_types.py
drf_typescript_generator/utils.py
drf_typescript_generator-0.1.1.dist-info/LICENSE
drf_typescript_generator-0.1.1.dist-info/WHEEL
drf_typescript_generator-0.1.1.dist-info/METADATA
drf_typescript_generator-0.1.1.dist-info/RECORD
