Metadata-Version: 2.1
Name: drf-typescript-generator
Version: 0.1.1
Summary: Package for generating TypeScript types from DRF serializers
Home-page: https://github.com/remastr/drf-typescript-generator
License: MIT
Keywords: django,drf
Author: napmn
Author-email: lukass135@gmail.com
Requires-Python: >=3.8,<4.0
Classifier: Environment :: Web Environment
Classifier: Framework :: Django
Classifier: License :: OSI Approved :: MIT License
Classifier: Programming Language :: Python :: 3
Classifier: Programming Language :: Python :: 3.8
Classifier: Programming Language :: Python :: 3.9
Requires-Dist: Django (>=3.2.4,<4.0.0)
Requires-Dist: djangorestframework (>=3.12.4,<4.0.0)
